alice/__init__.py
alice/__main__.py
alice/cli.py
alice/config.py
alice/configparser.py
alice/exceptions.py
alice/runnerfactory.py
alice/runners/__init__.py
alice/runners/dockerrunner.py
alice/runners/pypirepo.py
alice/runners/pypirunner.py
alice/runners/pythonrunner.py
alice/runners/pyutils.py
alice_ci-0.0.14.dist-info/METADATA
alice_ci-0.0.14.dist-info/WHEEL
alice_ci-0.0.14.dist-info/entry_points.txt
alice_ci-0.0.14.dist-info/top_level.txt
alice_ci-0.0.14.dist-info/RECORD
