Metadata-Version: 2.1
Name: alice-ci
Version: 0.0.14
Summary: Alice CI framework
Home-page: https://git.gyulai.cloud/gyulaid/alice
Author: Daniel Gyulai
License: UNKNOWN
Project-URL: Bug Tracker, https://git.gyulai.cloud/gyulaid/alice/issues
Platform: UNKNOWN
Classifier: Programming Language :: Python :: 3
Classifier: License :: OSI Approved :: MIT License
Classifier: Operating System :: OS Independent
Requires-Python: >=3.6
Requires-Dist: PyYAML
Requires-Dist: docker
